{"_invocation_id": "8833d466-c294-4e54-9710-dee28da4e366", "linked": {"0": {"name": "source.transform.rds.access_approval", "type": "source", "succ": [18, 34, 35, 36, 37, 38, 39, 40, 41, 42, 43, 44, 45, 46, 47, 48, 105]}, "1": {"name": "source.transform.rds.access_requirement", "type": "source", "succ": [19, 42, 49, 50, 51, 52, 53, 54, 55, 56, 57, 58, 60, 63, 87, 101, 110, 136]}, "2": {"name": "source.transform.rds.access_requirement_project", "type": "source", "succ": [23, 59, 60, 61]}, "3": {"name": "source.transform.rds.access_requirement_revision", "type": "source", "succ": [26, 62, 63, 64, 65, 66]}, "4": {"name": "source.transform.rds.acl", "type": "source", "succ": [17, 67, 68, 69, 70, 71, 72, 76, 81]}, "5": {"name": "source.transform.rds.acl_resource_access", "type": "source", "succ": [16, 73, 74, 75, 76, 77, 79]}, "6": {"name": "source.transform.rds.acl_resource_access_type", "type": "source", "succ": [15, 78, 79, 80, 81, 82, 83]}, "7": {"name": "source.transform.rds.data_access_request", "type": "source", "succ": [24, 84, 85, 86, 87, 88, 89, 90, 91, 92, 93, 94, 113]}, "8": {"name": "source.transform.rds.data_access_notification", "type": "source", "succ": [22, 95, 96, 97, 98, 99, 100, 101, 102, 103, 104, 105, 106]}, "9": {"name": "source.transform.rds.data_access_submission", "type": "source", "succ": [21, 107, 108, 109, 110, 111, 112, 113, 114, 115, 116, 117, 118, 120, 126, 139]}, "10": {"name": "source.transform.rds.data_access_submission_accessor_changes", "type": "source", "succ": [25, 119, 120, 121, 122, 123]}, "11": {"name": "source.transform.rds.data_access_submission_status", "type": "source", "succ": [20, 124, 125, 126, 127, 128, 129, 130, 131, 132]}, "12": {"name": "source.transform.rds.data_access_submission_submitter", "type": "source", "succ": [27, 133, 134, 135, 136, 137, 138, 139, 140]}, "13": {"name": "source.transform.rds.principal_alias", "type": "source", "succ": [14, 141, 142, 143, 144, 145, 146, 147, 148, 149]}, "14": {"name": "model.transform.stg_synapse__principal_alias", "type": "model", "succ": [29]}, "15": {"name": "model.transform.stg_synapse__acl_resource_access_type", "type": "model", "succ": [33]}, "16": {"name": "model.transform.stg_synapse__acl_resource_access", "type": "model", "succ": [15, 33]}, "17": {"name": "model.transform.stg_synapse__acl", "type": "model", "succ": [15, 16, 33]}, "18": {"name": "model.transform.stg_synapse__access_approval", "type": "model", "succ": [22]}, "19": {"name": "model.transform.stg_synapse__access_requirement", "type": "model", "succ": [18, 22, 23, 24, 26, 27, 21, 32]}, "20": {"name": "model.transform.stg_synapse__data_access_submission_status", "type": "model", "succ": [31]}, "21": {"name": "model.transform.stg_synapse__data_access_submission", "type": "model", "succ": [20, 25, 27, 31]}, "22": {"name": "model.transform.stg_synapse__data_access_notification", "type": "model"}, "23": {"name": "model.transform.stg_synapse__access_requirement_project", "type": "model"}, "24": {"name": "model.transform.stg_synapse__data_access_request", "type": "model", "succ": [21]}, "25": {"name": "model.transform.stg_synapse__data_access_submission_accessor_changes", "type": "model", "succ": [31]}, "26": {"name": "model.transform.stg_synapse__access_requirement_revision", "type": "model", "succ": [32]}, "27": {"name": "model.transform.stg_synapse__data_access_submission_submitter", "type": "model", "succ": [31]}, "28": {"name": "model.transform.data_access_submission_dashboard", "type": "model"}, "29": {"name": "model.transform.int_synapse_data_access_submission_enriched", "type": "model", "succ": [28, 30]}, "30": {"name": "model.transform.data_access_submission_event", "type": "model"}, "31": {"name": "model.transform.int_synapse_data_access_submission", "type": "model", "succ": [29]}, "32": {"name": "model.transform.int_synapse_access_requirement", "type": "model"}, "33": {"name": "model.transform.int_synapse_acl", "type": "model"}, "34": {"name": "test.transform.source_not_null_rds_access_approval_id.88b5bc0dbd", "type": "test"}, "35": {"name": "test.transform.source_unique_rds_access_approval_id.caf8984288", "type": "test"}, "36": {"name": "test.transform.source_not_null_rds_access_approval_etag.258cef3d4c", "type": "test"}, "37": {"name": "test.transform.source_not_null_rds_access_approval_created_by.fa536fa1e4", "type": "test"}, "38": {"name": "test.transform.source_not_null_rds_access_approval_created_on.1338b33ba4", "type": "test"}, "39": {"name": "test.transform.source_not_null_rds_access_approval_modified_by.c0cf073103", "type": "test"}, "40": {"name": "test.transform.source_not_null_rds_access_approval_modified_on.ccbc0328bc", "type": "test"}, "41": {"name": "test.transform.source_not_null_rds_access_approval_requirement_id.4e9ab698a1", "type": "test"}, "42": {"name": "test.transform.source_relationships_rds_access_approval_requirement_id__id__source_rds_access_requirement_.55dfca1254", "type": "test"}, "43": {"name": "test.transform.source_not_null_rds_access_approval_requirement_version.2492f0f4e5", "type": "test"}, "44": {"name": "test.transform.source_not_null_rds_access_approval_submitter_id.1daae36925", "type": "test"}, "45": {"name": "test.transform.source_not_null_rds_access_approval_accessor_id.55ef5e7403", "type": "test"}, "46": {"name": "test.transform.source_not_null_rds_access_approval_expired_on.c01a3a1d6c", "type": "test"}, "47": {"name": "test.transform.source_not_null_rds_access_approval_state.170eaeaf68", "type": "test"}, "48": {"name": "test.transform.source_accepted_values_rds_access_approval_state__APPROVED__REVOKED.9e489ef9c2", "type": "test"}, "49": {"name": "test.transform.source_not_null_rds_access_requirement_id.fb25ef231b", "type": "test"}, "50": {"name": "test.transform.source_unique_rds_access_requirement_id.3be94b8af1", "type": "test"}, "51": {"name": "test.transform.source_not_null_rds_access_requirement_etag.688e1e5dc4", "type": "test"}, "52": {"name": "test.transform.source_not_null_rds_access_requirement_name.cf57f66727", "type": "test"}, "53": {"name": "test.transform.source_unique_rds_access_requirement_name.e41036ef6e", "type": "test"}, "54": {"name": "test.transform.source_not_null_rds_access_requirement_created_by.f99738e8ba", "type": "test"}, "55": {"name": "test.transform.source_not_null_rds_access_requirement_created_on.caf9640d57", "type": "test"}, "56": {"name": "test.transform.source_not_null_rds_access_requirement_access_type.939bf4b86e", "type": "test"}, "57": {"name": "test.transform.source_accepted_values_rds_access_requirement_access_type__DOWNLOAD__PARTICIPATE.ab48984744", "type": "test"}, "58": {"name": "test.transform.source_not_null_rds_access_requirement_is_two_fa_required.fb9601b0fa", "type": "test"}, "59": {"name": "test.transform.source_not_null_rds_access_requirement_project_ar_id.41803b384d", "type": "test"}, "60": {"name": "test.transform.source_relationships_rds_access_requirement_project_ar_id__id__source_rds_access_requirement_.8c2cabd619", "type": "test"}, "61": {"name": "test.transform.source_not_null_rds_access_requirement_project_project_id.d9aa085f90", "type": "test"}, "62": {"name": "test.transform.source_not_null_rds_access_requirement_revision_owner_id.a22306347c", "type": "test"}, "63": {"name": "test.transform.source_relationships_rds_access_requirement_revision_owner_id__id__source_rds_access_requirement_.4d8469acb6", "type": "test"}, "64": {"name": "test.transform.source_not_null_rds_access_requirement_revision_number.779b0facbf", "type": "test"}, "65": {"name": "test.transform.source_not_null_rds_access_requirement_revision_modified_by.4c1f265e75", "type": "test"}, "66": {"name": "test.transform.source_not_null_rds_access_requirement_revision_modified_on.353e103f39", "type": "test"}, "67": {"name": "test.transform.source_not_null_rds_acl_id.5f015efa06", "type": "test"}, "68": {"name": "test.transform.source_unique_rds_acl_id.1b614eb21e", "type": "test"}, "69": {"name": "test.transform.source_not_null_rds_acl_owner_id.2096449ffa", "type": "test"}, "70": {"name": "test.transform.source_accepted_values_rds_acl_owner_type__ENTITY__EVALUATION__TEAM__FORM_GROUP__ORGANIZATION__ACCESS_REQUIREMENT__PORTAL__OAUTH_CLIENT.b07b1efae0", "type": "test"}, "71": {"name": "test.transform.source_not_null_rds_acl_etag.cfb5b8c8bd", "type": "test"}, "72": {"name": "test.transform.source_not_null_rds_acl_created_on.3e3792657f", "type": "test"}, "73": {"name": "test.transform.source_not_null_rds_acl_resource_access_id.f37f081e73", "type": "test"}, "74": {"name": "test.transform.source_unique_rds_acl_resource_access_id.524404161b", "type": "test"}, "75": {"name": "test.transform.source_not_null_rds_acl_resource_access_owner_id.d415de7e5e", "type": "test"}, "76": {"name": "test.transform.source_relationships_rds_acl_resource_access_owner_id__id__source_rds_acl_.a7c41c04bd", "type": "test"}, "77": {"name": "test.transform.source_not_null_rds_acl_resource_access_group_id.74be61251c", "type": "test"}, "78": {"name": "test.transform.source_not_null_rds_acl_resource_access_type_id_oid.32061b5f14", "type": "test"}, "79": {"name": "test.transform.source_relationships_rds_acl_resource_access_type_id_oid__id__source_rds_acl_resource_access_.5ab34ff227", "type": "test"}, "80": {"name": "test.transform.source_not_null_rds_acl_resource_access_type_owner_id.ca25ef8638", "type": "test"}, "81": {"name": "test.transform.source_relationships_rds_acl_resource_access_type_owner_id__id__source_rds_acl_.ea9ae8eb53", "type": "test"}, "82": {"name": "test.transform.source_not_null_rds_acl_resource_access_type_string_ele.b26bf52224", "type": "test"}, "83": {"name": "test.transform.source_accepted_values_rds_acl_resource_access_type_string_ele__CHANGE_PERMISSIONS__TEAM_MEMBERSHIP_UPDATE__MODERATE__SEND_MESSAGE__READ_PRIVATE_SUBMISSION__SUBMIT__CHANGE_SETTINGS__EXEMPTION_ELIGIBLE__PARTICIPATE__CREATE__DELETE__UPDATE__DELETE_SUBMISSION__DOWNLOAD__READ__UPDATE_SUBMISSION__REVIEW_SUBMISSIONS__UPLOAD.db7d484c43", "type": "test"}, "84": {"name": "test.transform.source_not_null_rds_data_access_request_id.98c92baae5", "type": "test"}, "85": {"name": "test.transform.source_unique_rds_data_access_request_id.b7ae4a651a", "type": "test"}, "86": {"name": "test.transform.source_not_null_rds_data_access_request_access_requirement_id.bbe1492ceb", "type": "test"}, "87": {"name": "test.transform.source_relationships_rds_data_access_request_access_requirement_id__id__source_rds_access_requirement_.b1081eac88", "type": "test"}, "88": {"name": "test.transform.source_not_null_rds_data_access_request_research_project_id.2fccc27172", "type": "test"}, "89": {"name": "test.transform.source_not_null_rds_data_access_request_created_by.ac67cbf204", "type": "test"}, "90": {"name": "test.transform.source_not_null_rds_data_access_request_created_on.29e9cbc629", "type": "test"}, "91": {"name": "test.transform.source_not_null_rds_data_access_request_modified_by.150236e637", "type": "test"}, "92": {"name": "test.transform.source_not_null_rds_data_access_request_modified_on.508296b198", "type": "test"}, "93": {"name": "test.transform.source_not_null_rds_data_access_request_etag.41ffdb3c4d", "type": "test"}, "94": {"name": "test.transform.source_not_null_rds_data_access_request_request_serialized.62128ca1aa", "type": "test"}, "95": {"name": "test.transform.source_not_null_rds_data_access_notification_id.536140c36c", "type": "test"}, "96": {"name": "test.transform.source_unique_rds_data_access_notification_id.7513fe79df", "type": "test"}, "97": {"name": "test.transform.source_not_null_rds_data_access_notification_etag.bfc7cf1841", "type": "test"}, "98": {"name": "test.transform.source_not_null_rds_data_access_notification_notification_type.7bfbae3d9f", "type": "test"}, "99": {"name": "test.transform.source_accepted_values_rds_data_access_notification_notification_type__FIRST_RENEWAL_REMINDER__SECOND_RENEWAL_REMINDER__REVOCATION.603b4544f2", "type": "test"}, "100": {"name": "test.transform.source_not_null_rds_data_access_notification_requirement_id.8642dd9e72", "type": "test"}, "101": {"name": "test.transform.source_relationships_rds_data_access_notification_requirement_id__id__source_rds_access_requirement_.736a4565db", "type": "test"}, "102": {"name": "test.transform.source_not_null_rds_data_access_notification_recipient_id.fcbd0cfbb0", "type": "test"}, "103": {"name": "test.transform.source_not_null_rds_data_access_notification_sent_on.9a8836f14f", "type": "test"}, "104": {"name": "test.transform.source_not_null_rds_data_access_notification_access_approval_id.91913e4012", "type": "test"}, "105": {"name": "test.transform.source_relationships_rds_data_access_notification_access_approval_id__id__source_rds_access_approval_.b50803fc2e", "type": "test"}, "106": {"name": "test.transform.source_not_null_rds_data_access_notification_message_id.1d2fb2c40f", "type": "test"}, "107": {"name": "test.transform.source_not_null_rds_data_access_submission_id.46eb169e9d", "type": "test"}, "108": {"name": "test.transform.source_unique_rds_data_access_submission_id.677f84a9a3", "type": "test"}, "109": {"name": "test.transform.source_not_null_rds_data_access_submission_access_requirement_id.79e40e9a98", "type": "test"}, "110": {"name": "test.transform.source_relationships_rds_data_access_submission_access_requirement_id__id__source_rds_access_requirement_.b57c399b4e", "type": "test"}, "111": {"name": "test.transform.source_not_null_rds_data_access_submission_access_requirement_version.eb7de03d12", "type": "test"}, "112": {"name": "test.transform.source_not_null_rds_data_access_submission_data_access_request_id.5278d1ebaf", "type": "test"}, "113": {"name": "test.transform.source_relationships_rds_data_access_submission_data_access_request_id__id__source_rds_data_access_request_.e11ba7ef73", "type": "test"}, "114": {"name": "test.transform.source_not_null_rds_data_access_submission_created_by.c7234adf9b", "type": "test"}, "115": {"name": "test.transform.source_not_null_rds_data_access_submission_created_on.bc151e28ca", "type": "test"}, "116": {"name": "test.transform.source_not_null_rds_data_access_submission_etag.42452194e3", "type": "test"}, "117": {"name": "test.transform.source_not_null_rds_data_access_submission_submission_serialized.c2bc9293f8", "type": "test"}, "118": {"name": "test.transform.source_not_null_rds_data_access_submission_research_project_id.9156e0971c", "type": "test"}, "119": {"name": "test.transform.source_not_null_rds_data_access_submission_accessor_changes_submission_id.d93b64b041", "type": "test"}, "120": {"name": "test.transform.source_relationships_rds_data_access_submission_accessor_changes_submission_id__id__source_rds_data_access_submission_.838ca36bb9", "type": "test"}, "121": {"name": "test.transform.source_not_null_rds_data_access_submission_accessor_changes_accessor_id.6680307048", "type": "test"}, "122": {"name": "test.transform.source_not_null_rds_data_access_submission_accessor_changes_access_type.d8b7decb17", "type": "test"}, "123": {"name": "test.transform.source_accepted_values_rds_data_access_submission_accessor_changes_access_type__GAIN_ACCESS__RENEW_ACCESS__REVOKE_ACCESS.b94f87f99c", "type": "test"}, "124": {"name": "test.transform.source_not_null_rds_data_access_submission_status_submission_id.3ec73be94f", "type": "test"}, "125": {"name": "test.transform.source_unique_rds_data_access_submission_status_submission_id.6ec8c4d2b1", "type": "test"}, "126": {"name": "test.transform.source_relationships_rds_data_access_submission_status_submission_id__id__source_rds_data_access_submission_.fd66e2ee3f", "type": "test"}, "127": {"name": "test.transform.source_not_null_rds_data_access_submission_status_created_by.60dbe1af51", "type": "test"}, "128": {"name": "test.transform.source_not_null_rds_data_access_submission_status_created_on.5caf95112d", "type": "test"}, "129": {"name": "test.transform.source_not_null_rds_data_access_submission_status_modified_by.b4a5a64cfa", "type": "test"}, "130": {"name": "test.transform.source_not_null_rds_data_access_submission_status_modified_on.6220378d97", "type": "test"}, "131": {"name": "test.transform.source_not_null_rds_data_access_submission_status_state.25b089afb9", "type": "test"}, "132": {"name": "test.transform.source_accepted_values_rds_data_access_submission_status_state__SUBMITTED__APPROVED__REJECTED__CANCELLED.2beb363b75", "type": "test"}, "133": {"name": "test.transform.source_not_null_rds_data_access_submission_submitter_id.741e416e10", "type": "test"}, "134": {"name": "test.transform.source_unique_rds_data_access_submission_submitter_id.b26142f15a", "type": "test"}, "135": {"name": "test.transform.source_not_null_rds_data_access_submission_submitter_access_requirement_id.8b2132804a", "type": "test"}, "136": {"name": "test.transform.source_relationships_rds_data_access_submission_submitter_access_requirement_id__id__source_rds_access_requirement_.58b6b003a1", "type": "test"}, "137": {"name": "test.transform.source_not_null_rds_data_access_submission_submitter_submitter_id.af80e05ee0", "type": "test"}, "138": {"name": "test.transform.source_not_null_rds_data_access_submission_submitter_current_submission_id.cb4aeb4f37", "type": "test"}, "139": {"name": "test.transform.source_relationships_rds_data_access_submission_submitter_current_submission_id__id__source_rds_data_access_submission_.29df4c88ec", "type": "test"}, "140": {"name": "test.transform.source_not_null_rds_data_access_submission_submitter_etag.52bada922c", "type": "test"}, "141": {"name": "test.transform.source_not_null_rds_principal_alias_id.1e80cf78c5", "type": "test"}, "142": {"name": "test.transform.source_unique_rds_principal_alias_id.0a99f2aa15", "type": "test"}, "143": {"name": "test.transform.source_not_null_rds_principal_alias_etag.f637271fa7", "type": "test"}, "144": {"name": "test.transform.source_not_null_rds_principal_alias_principal_id.53e75a4d05", "type": "test"}, "145": {"name": "test.transform.source_not_null_rds_principal_alias_alias_unique.81cb2f1f96", "type": "test"}, "146": {"name": "test.transform.source_unique_rds_principal_alias_alias_unique.a58c64c30d", "type": "test"}, "147": {"name": "test.transform.source_not_null_rds_principal_alias_alias_display.26a4e636ca", "type": "test"}, "148": {"name": "test.transform.source_not_null_rds_principal_alias_type.64de2624bf", "type": "test"}, "149": {"name": "test.transform.source_accepted_values_rds_principal_alias_type__USER_NAME__TEAM_NAME__USER_EMAIL__USER_OPEN_ID__USER_ORCID.1014ac996a", "type": "test"}}}